README.md
setup.py
KPDBL.egg-info/PKG-INFO
KPDBL.egg-info/SOURCES.txt
KPDBL.egg-info/dependency_links.txt
KPDBL.egg-info/top_level.txt
kpdbl/__init__.py